{
    "Current Courses": [
        "NTE1015",
        "ME4051"
    ],
    "Execution Trace": [
        "Offered Courses: ",
        "ATA122, CSE2246, CSE2138, EE2032, CSE3038, CSE3044, CSE3048, COM2202, ISG122, CSE4298(Final Project), ",
        "(1 NTE), (3 TE), (1 FTE), ",
        "",
        "The system didn't allow ATA122 because course section is full. (100)",
        "The system didn't allow CSE2246 because course section is full. (100)",
        "The system didn't allow CSE2138 because course section is full. (100)",
        "The system didn't allow EE2032 because course section is full. (100)",
        "The system didn't allow CSE3038 because student failed prerequisites -> CSE2138 ",
        "The system didn't allow CSE3044 because student failed prerequisites -> CSE3055 ",
        "The system didn't allow CSE3048 because student failed prerequisites -> MATH2055 ",
        "The system didn't allow COM2202 because course section is full. (100)",
        "The system didn't allow ISG122 because course section is full. (100)",
        "The system didn't allow CSE4298(Final Project) because Student completed credits is less than 165-> (139)",
        "The system didn't allow CSE4044(TE) because Student completed credits is less than 155 -> (139)",
        "The system didn't allow CSE4053(TE) because Student completed credits is less than 155 -> (139)",
        "The system didn't allow CSE4086(TE) because Student completed credits is less than 155 -> (139)",
        "",
        "Current Courses: ",
        "NTE1015(NTE/UE), ME4051(FTE), "
    ],
    "AdvisorName": "NAFİYE ASLANALP",
    "SemesterNumber": 8,
    "Past Courses": [
        {
            "intGrade": 61,
            "Course": "ATA121",
            "LetterGrade": "DC"
        },
        {
            "intGrade": 74,
            "Course": "MBG1201",
            "LetterGrade": "CC"
        },
        {
            "intGrade": 19,
            "Course": "CSE1200",
            "LetterGrade": "FF"
        },
        {
            "intGrade": 60,
            "Course": "CSE1241",
            "LetterGrade": "DC"
        },
        {
            "intGrade": 71,
            "Course": "MATH1001",
            "LetterGrade": "CC"
        },
        {
            "intGrade": 58,
            "Course": "PHYS1101",
            "LetterGrade": "DC"
        },
        {
            "intGrade": 100,
            "Course": "PHYS1103",
            "LetterGrade": "AA"
        },
        {
            "intGrade": 72,
            "Course": "TRD121",
            "LetterGrade": "CC"
        },
        {
            "intGrade": 1,
            "Course": "ATA122",
            "LetterGrade": "FF"
        },
        {
            "intGrade": 96,
            "Course": "CSE1242",
            "LetterGrade": "AA"
        },
        {
            "intGrade": 94,
            "Course": "MATH1002",
            "LetterGrade": "AA"
        },
        {
            "intGrade": 96,
            "Course": "MATH2256",
            "LetterGrade": "AA"
        },
        {
            "intGrade": 59,
            "Course": "PHYS1102",
            "LetterGrade": "DC"
        },
        {
            "intGrade": 88,
            "Course": "PHYS1104",
            "LetterGrade": "BA"
        },
        {
            "intGrade": 69,
            "Course": "TRD122",
            "LetterGrade": "CC"
        },
        {
            "intGrade": 97,
            "Course": "CSE2023",
            "LetterGrade": "AA"
        },
        {
            "intGrade": 94,
            "Course": "CSE2225",
            "LetterGrade": "AA"
        },
        {
            "intGrade": 84,
            "Course": "ECON2004",
            "LetterGrade": "BB"
        },
        {
            "intGrade": 87,
            "Course": "EE2031",
            "LetterGrade": "BA"
        },
        {
            "intGrade": 3,
            "Course": "MATH2055",
            "LetterGrade": "FF"
        },
        {
            "intGrade": 7,
            "Course": "MATH2059",
            "LetterGrade": "FF"
        },
        {
            "intGrade": 37,
            "Course": "CSE2246",
            "LetterGrade": "FF"
        },
        {
            "intGrade": 39,
            "Course": "CSE2138",
            "LetterGrade": "FF"
        },
        {
            "intGrade": 53,
            "Course": "CSE2260",
            "LetterGrade": "DD"
        },
        {
            "intGrade": 12,
            "Course": "EE2032",
            "LetterGrade": "FF"
        },
        {
            "intGrade": 52,
            "Course": "STAT2253",
            "LetterGrade": "DD"
        },
        {
            "intGrade": 73,
            "Course": "CSE3000",
            "LetterGrade": "CC"
        },
        {
            "intGrade": 93,
            "Course": "CSE3215",
            "LetterGrade": "AA"
        },
        {
            "intGrade": 69,
            "Course": "CSE3033",
            "LetterGrade": "CC"
        },
        {
            "intGrade": 25,
            "Course": "CSE3055",
            "LetterGrade": "FF"
        },
        {
            "intGrade": 76,
            "Course": "CSE3063",
            "LetterGrade": "CB"
        },
        {
            "intGrade": 91,
            "Course": "IE3081",
            "LetterGrade": "AA"
        },
        {
            "intGrade": 87,
            "Course": "CSE3264",
            "LetterGrade": "BA"
        },
        {
            "intGrade": 55,
            "Course": "IE3235",
            "LetterGrade": "DC"
        },
        {
            "intGrade": 42,
            "Course": "COM2202",
            "LetterGrade": "FF"
        },
        {
            "intGrade": 96,
            "Course": "CSE4000",
            "LetterGrade": "AA"
        },
        {
            "intGrade": 4,
            "Course": "CSE4074",
            "LetterGrade": "FF"
        },
        {
            "intGrade": 91,
            "Course": "ISG121",
            "LetterGrade": "AA"
        },
        {
            "intGrade": 13,
            "Course": "CSE4288",
            "LetterGrade": "FF"
        },
        {
            "intGrade": 70,
            "Course": "YDF1001",
            "LetterGrade": "CC"
        },
        {
            "intGrade": 28,
            "Course": "YDIS1001",
            "LetterGrade": "FF"
        }
    ],
    "StudentName": "ÖMER FARUK TUNCEL",
    "CompletedCredits": 139,
    "StudentId": "150117226"
}