{
    "Current Courses": [
        "CSE1200",
        "TRD121",
        "CSE2225",
        "CSE3063",
        "IE3081"
    ],
    "Execution Trace": [
        "Offered Courses: ",
        "CSE1200, TRD121, CSE2225, CSE3215, CSE3033, CSE3055, CSE3063, IE3081, ",
        "(0 NTE), (0 TE), (0 FTE), ",
        "",
        "Advisor didn't approve CSE3215 because of more than one hour collision with -> CSE2225 CSE1200  in schedule",
        "The system didn't allow CSE3033 because student failed prerequisites -> CSE2225 ",
        "The system didn't allow CSE3055 because student failed prerequisites -> CSE2225 ",
        "",
        "Current Courses: ",
        "CSE1200, TRD121, CSE2225, CSE3063, IE3081, "
    ],
    "AdvisorName": "MUSTAFA KEMAL",
    "SemesterNumber": 5,
    "Past Courses": [
        {
            "intGrade": 51,
            "Course": "ATA121",
            "LetterGrade": "DD"
        },
        {
            "intGrade": 87,
            "Course": "MBG1201",
            "LetterGrade": "BA"
        },
        {
            "intGrade": 44,
            "Course": "CSE1200",
            "LetterGrade": "FF"
        },
        {
            "intGrade": 56,
            "Course": "CSE1241",
            "LetterGrade": "DC"
        },
        {
            "intGrade": 85,
            "Course": "MATH1001",
            "LetterGrade": "BA"
        },
        {
            "intGrade": 66,
            "Course": "PHYS1101",
            "LetterGrade": "CC"
        },
        {
            "intGrade": 83,
            "Course": "PHYS1103",
            "LetterGrade": "BB"
        },
        {
            "intGrade": 38,
            "Course": "TRD121",
            "LetterGrade": "FF"
        },
        {
            "intGrade": 57,
            "Course": "ATA122",
            "LetterGrade": "DC"
        },
        {
            "intGrade": 97,
            "Course": "CSE1242",
            "LetterGrade": "AA"
        },
        {
            "intGrade": 76,
            "Course": "MATH1002",
            "LetterGrade": "CB"
        },
        {
            "intGrade": 65,
            "Course": "MATH2256",
            "LetterGrade": "CC"
        },
        {
            "intGrade": 86,
            "Course": "PHYS1102",
            "LetterGrade": "BA"
        },
        {
            "intGrade": 82,
            "Course": "PHYS1104",
            "LetterGrade": "BB"
        },
        {
            "intGrade": 75,
            "Course": "TRD122",
            "LetterGrade": "CB"
        },
        {
            "intGrade": 70,
            "Course": "CSE2023",
            "LetterGrade": "CC"
        },
        {
            "intGrade": 40,
            "Course": "CSE2225",
            "LetterGrade": "FF"
        },
        {
            "intGrade": 97,
            "Course": "ECON2004",
            "LetterGrade": "AA"
        },
        {
            "intGrade": 69,
            "Course": "EE2031",
            "LetterGrade": "CC"
        },
        {
            "intGrade": 93,
            "Course": "MATH2055",
            "LetterGrade": "AA"
        },
        {
            "intGrade": 86,
            "Course": "MATH2059",
            "LetterGrade": "BA"
        },
        {
            "intGrade": 53,
            "Course": "CSE2246",
            "LetterGrade": "DD"
        },
        {
            "intGrade": 78,
            "Course": "CSE2138",
            "LetterGrade": "CB"
        },
        {
            "intGrade": 70,
            "Course": "CSE2260",
            "LetterGrade": "CC"
        },
        {
            "intGrade": 37,
            "Course": "EE2032",
            "LetterGrade": "FF"
        },
        {
            "intGrade": 100,
            "Course": "STAT2253",
            "LetterGrade": "AA"
        },
        {
            "intGrade": 61,
            "Course": "CSE3000",
            "LetterGrade": "DC"
        },
        {
            "intGrade": 57,
            "Course": "HSS3002",
            "LetterGrade": "DC"
        }
    ],
    "StudentName": "SELMA",
    "StudentSurname": "SELVİ",
    "CompletedCredits": 110,
    "StudentId": "150118089",
    "AdvisorSurname": "DİLLİ"
}