{
    "Current Courses": [
        "CSE3215",
        "CSE3033",
        "CSE3055",
        "CSE3063",
        "IE3081"
    ],
    "Execution Trace": [
        "Offered Courses: ",
        "PHYS1101, PHYS1103, CSE3215, CSE3033, CSE3055, CSE3063, IE3081, ",
        "(0 NTE), (0 TE), (0 FTE), ",
        "",
        "The system didn't allow PHYS1101 because course section is full. (100)",
        "The system didn't allow PHYS1103 because course section is full. (100)",
        "",
        "Current Courses: ",
        "CSE3215, CSE3033, CSE3055, CSE3063, IE3081, "
    ],
    "AdvisorName": "SUNA",
    "SemesterNumber": 5,
    "Past Courses": [
        {
            "intGrade": 78,
            "Course": "ATA121",
            "LetterGrade": "CB"
        },
        {
            "intGrade": 51,
            "Course": "MBG1201",
            "LetterGrade": "DD"
        },
        {
            "intGrade": 97,
            "Course": "CSE1200",
            "LetterGrade": "AA"
        },
        {
            "intGrade": 88,
            "Course": "CSE1241",
            "LetterGrade": "BA"
        },
        {
            "intGrade": 85,
            "Course": "MATH1001",
            "LetterGrade": "BA"
        },
        {
            "intGrade": 16,
            "Course": "PHYS1101",
            "LetterGrade": "FF"
        },
        {
            "intGrade": 37,
            "Course": "PHYS1103",
            "LetterGrade": "FF"
        },
        {
            "intGrade": 76,
            "Course": "TRD121",
            "LetterGrade": "CB"
        },
        {
            "intGrade": 52,
            "Course": "ATA122",
            "LetterGrade": "DD"
        },
        {
            "intGrade": 96,
            "Course": "CSE1242",
            "LetterGrade": "AA"
        },
        {
            "intGrade": 37,
            "Course": "MATH1002",
            "LetterGrade": "FF"
        },
        {
            "intGrade": 36,
            "Course": "MATH2256",
            "LetterGrade": "FF"
        },
        {
            "intGrade": 71,
            "Course": "PHYS1102",
            "LetterGrade": "CC"
        },
        {
            "intGrade": 76,
            "Course": "PHYS1104",
            "LetterGrade": "CB"
        },
        {
            "intGrade": 77,
            "Course": "TRD122",
            "LetterGrade": "CB"
        },
        {
            "intGrade": 78,
            "Course": "CSE2023",
            "LetterGrade": "CB"
        },
        {
            "intGrade": 57,
            "Course": "CSE2225",
            "LetterGrade": "DC"
        },
        {
            "intGrade": 79,
            "Course": "ECON2004",
            "LetterGrade": "CB"
        },
        {
            "intGrade": 80,
            "Course": "EE2031",
            "LetterGrade": "BB"
        },
        {
            "intGrade": 67,
            "Course": "MATH2055",
            "LetterGrade": "CC"
        },
        {
            "intGrade": 56,
            "Course": "MATH2059",
            "LetterGrade": "DC"
        },
        {
            "intGrade": 90,
            "Course": "CSE2246",
            "LetterGrade": "AA"
        },
        {
            "intGrade": 84,
            "Course": "CSE2138",
            "LetterGrade": "BB"
        },
        {
            "intGrade": 18,
            "Course": "CSE2260",
            "LetterGrade": "FF"
        },
        {
            "intGrade": 30,
            "Course": "EE2032",
            "LetterGrade": "FF"
        },
        {
            "intGrade": 89,
            "Course": "STAT2253",
            "LetterGrade": "BA"
        },
        {
            "intGrade": 86,
            "Course": "CSE3000",
            "LetterGrade": "BA"
        },
        {
            "intGrade": 98,
            "Course": "NTE1013",
            "LetterGrade": "AA"
        }
    ],
    "StudentName": "MAHİR",
    "StudentSurname": "KARAKILIÇ",
    "CompletedCredits": 102,
    "StudentId": "150118048",
    "AdvisorSurname": "YÜKSEL"
}