{
    "Current Courses": [
        "CSE2023",
        "ECON2004",
        "EE2031",
        "MATH2055",
        "MATH2059"
    ],
    "Execution Trace": [
        "Offered Courses: ",
        "MBG1201, CSE2023, CSE2225, ECON2004, EE2031, MATH2055, MATH2059, ",
        "(0 NTE), (0 TE), (0 FTE), ",
        "",
        "The system didn't allow MBG1201 because course section is full. (100)",
        "The system didn't allow CSE2225 because student failed prerequisites -> CSE1242 ",
        "",
        "Current Courses: ",
        "CSE2023, ECON2004, EE2031, MATH2055, MATH2059, "
    ],
    "AdvisorName": "ZEHRA BETÜL",
    "SemesterNumber": 3,
    "Past Courses": [
        {
            "intGrade": 78,
            "Course": "ATA121",
            "LetterGrade": "CB"
        },
        {
            "intGrade": 20,
            "Course": "MBG1201",
            "LetterGrade": "FF"
        },
        {
            "intGrade": 77,
            "Course": "CSE1200",
            "LetterGrade": "CB"
        },
        {
            "intGrade": 64,
            "Course": "CSE1241",
            "LetterGrade": "DC"
        },
        {
            "intGrade": 57,
            "Course": "MATH1001",
            "LetterGrade": "DC"
        },
        {
            "intGrade": 57,
            "Course": "PHYS1101",
            "LetterGrade": "DC"
        },
        {
            "intGrade": 59,
            "Course": "PHYS1103",
            "LetterGrade": "DC"
        },
        {
            "intGrade": 97,
            "Course": "TRD121",
            "LetterGrade": "AA"
        },
        {
            "intGrade": 17,
            "Course": "ATA122",
            "LetterGrade": "FF"
        },
        {
            "intGrade": 47,
            "Course": "CSE1242",
            "LetterGrade": "FD"
        },
        {
            "intGrade": 92,
            "Course": "MATH1002",
            "LetterGrade": "AA"
        },
        {
            "intGrade": 74,
            "Course": "MATH2256",
            "LetterGrade": "CC"
        },
        {
            "intGrade": 94,
            "Course": "PHYS1102",
            "LetterGrade": "AA"
        },
        {
            "intGrade": 11,
            "Course": "PHYS1104",
            "LetterGrade": "FF"
        },
        {
            "intGrade": 66,
            "Course": "TRD122",
            "LetterGrade": "CC"
        },
        {
            "intGrade": 80,
            "Course": "CAS1010",
            "LetterGrade": "BB"
        }
    ],
    "StudentName": "YUSUF",
    "StudentSurname": "ÖNVERMEZ",
    "CompletedCredits": 46,
    "StudentId": "150119098",
    "AdvisorSurname": "GÖKSEL"
}