{
    "Current Courses": [
        "CSE3215",
        "IE3081"
    ],
    "Execution Trace": [
        "Offered Courses: ",
        "CSE1241, CSE2225, CSE3215, CSE3033, CSE3055, CSE3063, IE3081, ",
        "(0 NTE), (0 TE), (0 FTE), ",
        "",
        "The system didn't allow CSE1241 because course section is full. (100)",
        "The system didn't allow CSE2225 because student failed prerequisites -> CSE1242 ",
        "The system didn't allow CSE3033 because student failed prerequisites -> CSE2225 ",
        "The system didn't allow CSE3055 because student failed prerequisites -> CSE2225 ",
        "The system didn't allow CSE3063 because student failed prerequisites -> CSE1242 ",
        "",
        "Current Courses: ",
        "CSE3215, IE3081, "
    ],
    "AdvisorName": "MEHMET GÖKÇE",
    "SemesterNumber": 5,
    "Past Courses": [
        {
            "intGrade": 98,
            "Course": "ATA121",
            "LetterGrade": "AA"
        },
        {
            "intGrade": 84,
            "Course": "MBG1201",
            "LetterGrade": "BB"
        },
        {
            "intGrade": 89,
            "Course": "CSE1200",
            "LetterGrade": "BA"
        },
        {
            "intGrade": 6,
            "Course": "CSE1241",
            "LetterGrade": "FF"
        },
        {
            "intGrade": 95,
            "Course": "MATH1001",
            "LetterGrade": "AA"
        },
        {
            "intGrade": 59,
            "Course": "PHYS1101",
            "LetterGrade": "DC"
        },
        {
            "intGrade": 70,
            "Course": "PHYS1103",
            "LetterGrade": "CC"
        },
        {
            "intGrade": 78,
            "Course": "TRD121",
            "LetterGrade": "CB"
        },
        {
            "intGrade": 99,
            "Course": "ATA122",
            "LetterGrade": "AA"
        },
        {
            "intGrade": 95,
            "Course": "MATH1002",
            "LetterGrade": "AA"
        },
        {
            "intGrade": 87,
            "Course": "MATH2256",
            "LetterGrade": "BA"
        },
        {
            "intGrade": 84,
            "Course": "PHYS1102",
            "LetterGrade": "BB"
        },
        {
            "intGrade": 59,
            "Course": "PHYS1104",
            "LetterGrade": "DC"
        },
        {
            "intGrade": 56,
            "Course": "TRD122",
            "LetterGrade": "DC"
        },
        {
            "intGrade": 80,
            "Course": "CSE2023",
            "LetterGrade": "BB"
        },
        {
            "intGrade": 70,
            "Course": "ECON2004",
            "LetterGrade": "CC"
        },
        {
            "intGrade": 80,
            "Course": "EE2031",
            "LetterGrade": "BB"
        },
        {
            "intGrade": 70,
            "Course": "MATH2055",
            "LetterGrade": "CC"
        },
        {
            "intGrade": 96,
            "Course": "MATH2059",
            "LetterGrade": "AA"
        },
        {
            "intGrade": 57,
            "Course": "CSE2246",
            "LetterGrade": "DC"
        },
        {
            "intGrade": 78,
            "Course": "CSE2138",
            "LetterGrade": "CB"
        },
        {
            "intGrade": 100,
            "Course": "EE2032",
            "LetterGrade": "AA"
        },
        {
            "intGrade": 77,
            "Course": "STAT2253",
            "LetterGrade": "CB"
        },
        {
            "intGrade": 80,
            "Course": "CSE3000",
            "LetterGrade": "BB"
        },
        {
            "intGrade": 94,
            "Course": "CAS2001",
            "LetterGrade": "AA"
        }
    ],
    "StudentName": "SEMİNE",
    "StudentSurname": "MUTLU",
    "CompletedCredits": 105,
    "StudentId": "150118024",
    "AdvisorSurname": "ALTUN"
}