{
    "Current Courses": [
        "MBG1201",
        "CSE1241",
        "CSE2023",
        "ECON2004",
        "EE2031",
        "MATH2055",
        "MATH2059"
    ],
    "Execution Trace": [
        "Current Semester Courses: ",
        "MBG1201, CSE1241, CSE2023, CSE2225, ECON2004, EE2031, MATH2055, MATH2059, ",
        "(0 NTE), (0 TE), (0 FTE), ",
        "",
        "The system didn't allow CSE2225 because student failed prerequisites -> CSE1242 ",
        "",
        "Current Courses: ",
        "MBG1201, CSE1241, CSE2023, ECON2004, EE2031, MATH2055, MATH2059, "
    ],
    "AdvisorName": "BARIŞ AK",
    "SemesterNumber": 3,
    "Past Courses": [
        {
            "intGrade": 53,
            "LetterGrade": "DD",
            "Course": "ATA121"
        },
        {
            "intGrade": 6,
            "LetterGrade": "FF",
            "Course": "MBG1201"
        },
        {
            "intGrade": 57,
            "LetterGrade": "DC",
            "Course": "CSE1200"
        },
        {
            "intGrade": 8,
            "LetterGrade": "FF",
            "Course": "CSE1241"
        },
        {
            "intGrade": 77,
            "LetterGrade": "CB",
            "Course": "MATH1001"
        },
        {
            "intGrade": 75,
            "LetterGrade": "CB",
            "Course": "PHYS1101"
        },
        {
            "intGrade": 81,
            "LetterGrade": "BB",
            "Course": "PHYS1103"
        },
        {
            "intGrade": 80,
            "LetterGrade": "BB",
            "Course": "TRD121"
        },
        {
            "intGrade": 46,
            "LetterGrade": "FD",
            "Course": "ATA122"
        },
        {
            "intGrade": 99,
            "LetterGrade": "AA",
            "Course": "MATH1002"
        },
        {
            "intGrade": 85,
            "LetterGrade": "BA",
            "Course": "MATH2256"
        },
        {
            "intGrade": 79,
            "LetterGrade": "CB",
            "Course": "PHYS1102"
        },
        {
            "intGrade": 92,
            "LetterGrade": "AA",
            "Course": "PHYS1104"
        },
        {
            "intGrade": 98,
            "LetterGrade": "AA",
            "Course": "TRD122"
        },
        {
            "intGrade": 19,
            "LetterGrade": "FF",
            "Course": "NTE1012"
        }
    ],
    "StudentName": "ARZU DİLLİ",
    "CompletedCredits": 39,
    "StudentId": "150119036"
}