{
    "Current Courses": [
        "MATH1001",
        "CSE2023",
        "CSE2225",
        "ECON2004",
        "MATH2055"
    ],
    "Execution Trace": [
        "Offered Courses: ",
        "MATH1001, CSE2023, CSE2225, ECON2004, EE2031, MATH2055, MATH2059, ",
        "(0 NTE), (0 TE), (0 FTE), ",
        "",
        "The system didn't allow EE2031 because student failed prerequisites -> PHYS1102 ",
        "The system didn't allow MATH2059 because student failed prerequisites -> MATH1001 ",
        "",
        "Current Courses: ",
        "MATH1001, CSE2023, CSE2225, ECON2004, MATH2055, "
    ],
    "AdvisorName": "HİKMET",
    "SemesterNumber": 3,
    "Past Courses": [
        {
            "intGrade": 57,
            "Course": "ATA121",
            "LetterGrade": "DC"
        },
        {
            "intGrade": 92,
            "Course": "MBG1201",
            "LetterGrade": "AA"
        },
        {
            "intGrade": 92,
            "Course": "CSE1200",
            "LetterGrade": "AA"
        },
        {
            "intGrade": 91,
            "Course": "CSE1241",
            "LetterGrade": "AA"
        },
        {
            "intGrade": 33,
            "Course": "MATH1001",
            "LetterGrade": "FF"
        },
        {
            "intGrade": 90,
            "Course": "PHYS1101",
            "LetterGrade": "AA"
        },
        {
            "intGrade": 73,
            "Course": "PHYS1103",
            "LetterGrade": "CC"
        },
        {
            "intGrade": 91,
            "Course": "TRD121",
            "LetterGrade": "AA"
        },
        {
            "intGrade": 88,
            "Course": "ATA122",
            "LetterGrade": "BA"
        },
        {
            "intGrade": 91,
            "Course": "CSE1242",
            "LetterGrade": "AA"
        },
        {
            "intGrade": 67,
            "Course": "MATH1002",
            "LetterGrade": "CC"
        },
        {
            "intGrade": 62,
            "Course": "MATH2256",
            "LetterGrade": "DC"
        },
        {
            "intGrade": 44,
            "Course": "PHYS1102",
            "LetterGrade": "FF"
        },
        {
            "intGrade": 86,
            "Course": "PHYS1104",
            "LetterGrade": "BA"
        },
        {
            "intGrade": 73,
            "Course": "TRD122",
            "LetterGrade": "CC"
        },
        {
            "intGrade": 100,
            "Course": "YDA1002",
            "LetterGrade": "AA"
        }
    ],
    "StudentName": "ÖZDEN",
    "StudentSurname": "SAYGIN",
    "CompletedCredits": 51,
    "StudentId": "150119083",
    "AdvisorSurname": "SARAL"
}