{
    "Current Courses": [
        "CSE4074",
        "CSE4219",
        "ISG121",
        "CSE4288",
        "YDI1004"
    ],
    "Execution Trace": [
        "Offered Courses: ",
        "CSE1241, CSE2023, CSE2225, EE2031, CSE3033, CSE3055, CSE3063, CSE4074, CSE4219, ISG121, CSE4288, CSE4297(Final Project), ",
        "(1 NTE), (1 TE), (0 FTE), ",
        "",
        "The system didn't allow CSE1241 because course section is full. (100)",
        "The system didn't allow CSE2023 because course section is full. (100)",
        "The system didn't allow CSE2225 because student failed prerequisites -> CSE1242 ",
        "The system didn't allow EE2031 because student failed prerequisites -> PHYS1102 ",
        "The system didn't allow CSE3033 because student failed prerequisites -> CSE2225 ",
        "The system didn't allow CSE3055 because student failed prerequisites -> CSE2225 ",
        "The system didn't allow CSE3063 because student failed prerequisites -> CSE1242 ",
        "The system didn't allow CSE4297(Final Project) because Student completed credits is less than 165-> (121)",
        "The system didn't allow CSE4067(TE) because Student completed credits is less than 155 -> (121)",
        "",
        "Current Courses: ",
        "CSE4074, CSE4219, ISG121, CSE4288, YDI1004(NTE/UE), "
    ],
    "AdvisorName": "MEHMET",
    "SemesterNumber": 7,
    "Past Courses": [
        {
            "intGrade": 57,
            "Course": "ATA121",
            "LetterGrade": "DC"
        },
        {
            "intGrade": 58,
            "Course": "MBG1201",
            "LetterGrade": "DC"
        },
        {
            "intGrade": 84,
            "Course": "CSE1200",
            "LetterGrade": "BB"
        },
        {
            "intGrade": 36,
            "Course": "CSE1241",
            "LetterGrade": "FF"
        },
        {
            "intGrade": 55,
            "Course": "MATH1001",
            "LetterGrade": "DC"
        },
        {
            "intGrade": 50,
            "Course": "PHYS1101",
            "LetterGrade": "DD"
        },
        {
            "intGrade": 83,
            "Course": "PHYS1103",
            "LetterGrade": "BB"
        },
        {
            "intGrade": 96,
            "Course": "TRD121",
            "LetterGrade": "AA"
        },
        {
            "intGrade": 64,
            "Course": "ATA122",
            "LetterGrade": "DC"
        },
        {
            "intGrade": 68,
            "Course": "MATH1002",
            "LetterGrade": "CC"
        },
        {
            "intGrade": 99,
            "Course": "MATH2256",
            "LetterGrade": "AA"
        },
        {
            "intGrade": 25,
            "Course": "PHYS1102",
            "LetterGrade": "FF"
        },
        {
            "intGrade": 90,
            "Course": "PHYS1104",
            "LetterGrade": "AA"
        },
        {
            "intGrade": 46,
            "Course": "TRD122",
            "LetterGrade": "FD"
        },
        {
            "intGrade": 42,
            "Course": "CSE2023",
            "LetterGrade": "FF"
        },
        {
            "intGrade": 58,
            "Course": "ECON2004",
            "LetterGrade": "DC"
        },
        {
            "intGrade": 51,
            "Course": "MATH2055",
            "LetterGrade": "DD"
        },
        {
            "intGrade": 53,
            "Course": "MATH2059",
            "LetterGrade": "DD"
        },
        {
            "intGrade": 54,
            "Course": "CSE2246",
            "LetterGrade": "DD"
        },
        {
            "intGrade": 52,
            "Course": "CSE2138",
            "LetterGrade": "DD"
        },
        {
            "intGrade": 60,
            "Course": "STAT2253",
            "LetterGrade": "DC"
        },
        {
            "intGrade": 74,
            "Course": "CSE3000",
            "LetterGrade": "CC"
        },
        {
            "intGrade": 53,
            "Course": "CSE3215",
            "LetterGrade": "DD"
        },
        {
            "intGrade": 95,
            "Course": "IE3081",
            "LetterGrade": "AA"
        },
        {
            "intGrade": 57,
            "Course": "CSE3038",
            "LetterGrade": "DC"
        },
        {
            "intGrade": 72,
            "Course": "CSE3048",
            "LetterGrade": "CC"
        },
        {
            "intGrade": 85,
            "Course": "IE3235",
            "LetterGrade": "BA"
        },
        {
            "intGrade": 51,
            "Course": "COM2202",
            "LetterGrade": "DD"
        },
        {
            "intGrade": 93,
            "Course": "CSE4000",
            "LetterGrade": "AA"
        },
        {
            "intGrade": 68,
            "Course": "SOC3082",
            "LetterGrade": "CC"
        }
    ],
    "StudentName": "UYSAN",
    "StudentSurname": "ÖNEY KURNAZ",
    "CompletedCredits": 121,
    "StudentId": "150117028",
    "AdvisorSurname": "KUTLUCAN BAĞCI"
}