{
    "Current Courses": [
        "ATA121",
        "MBG1201",
        "CSE2023",
        "ECON2004",
        "EE2031",
        "MATH2055",
        "MATH2059"
    ],
    "Execution Trace": [
        "Offered Courses: ",
        "ATA121, MBG1201, CSE2023, CSE2225, ECON2004, EE2031, MATH2055, MATH2059, ",
        "(0 NTE), (0 TE), (0 FTE), ",
        "",
        "The system didn't allow CSE2225 because student failed prerequisites -> CSE1242 ",
        "",
        "Current Courses: ",
        "ATA121, MBG1201, CSE2023, ECON2004, EE2031, MATH2055, MATH2059, "
    ],
    "AdvisorName": "MUSTAFA KEMAL",
    "SemesterNumber": 3,
    "Past Courses": [
        {
            "intGrade": 25,
            "Course": "ATA121",
            "LetterGrade": "FF"
        },
        {
            "intGrade": 13,
            "Course": "MBG1201",
            "LetterGrade": "FF"
        },
        {
            "intGrade": 59,
            "Course": "CSE1200",
            "LetterGrade": "DC"
        },
        {
            "intGrade": 72,
            "Course": "CSE1241",
            "LetterGrade": "CC"
        },
        {
            "intGrade": 70,
            "Course": "MATH1001",
            "LetterGrade": "CC"
        },
        {
            "intGrade": 100,
            "Course": "PHYS1101",
            "LetterGrade": "AA"
        },
        {
            "intGrade": 68,
            "Course": "PHYS1103",
            "LetterGrade": "CC"
        },
        {
            "intGrade": 55,
            "Course": "TRD121",
            "LetterGrade": "DC"
        },
        {
            "intGrade": 8,
            "Course": "ATA122",
            "LetterGrade": "FF"
        },
        {
            "intGrade": 39,
            "Course": "CSE1242",
            "LetterGrade": "FF"
        },
        {
            "intGrade": 91,
            "Course": "MATH1002",
            "LetterGrade": "AA"
        },
        {
            "intGrade": 23,
            "Course": "MATH2256",
            "LetterGrade": "FF"
        },
        {
            "intGrade": 53,
            "Course": "PHYS1102",
            "LetterGrade": "DD"
        },
        {
            "intGrade": 30,
            "Course": "PHYS1104",
            "LetterGrade": "FF"
        },
        {
            "intGrade": 82,
            "Course": "TRD122",
            "LetterGrade": "BB"
        },
        {
            "intGrade": 28,
            "Course": "BUS2005",
            "LetterGrade": "FF"
        }
    ],
    "StudentName": "KADİR",
    "StudentSurname": "AKPINAR",
    "CompletedCredits": 36,
    "StudentId": "150119098",
    "AdvisorSurname": "DİLLİ"
}