{
    "Current Courses": [
        "CSE3215",
        "IE3081"
    ],
    "Execution Trace": [
        "Offered Courses: ",
        "ATA121, CSE1241, PHYS1101, PHYS1103, CSE2023, CSE2225, CSE3215, CSE3033, CSE3055, CSE3063, IE3081, ",
        "(0 NTE), (0 TE), (0 FTE), ",
        "",
        "The system didn't allow ATA121 because course section is full. (100)",
        "The system didn't allow CSE1241 because course section is full. (100)",
        "The system didn't allow PHYS1101 because course section is full. (100)",
        "The system didn't allow PHYS1103 because course section is full. (100)",
        "The system didn't allow CSE2023 because course section is full. (100)",
        "The system didn't allow CSE2225 because student failed prerequisites -> CSE1242 ",
        "The system didn't allow CSE3033 because student failed prerequisites -> CSE2225 ",
        "The system didn't allow CSE3055 because student failed prerequisites -> CSE2225 ",
        "The system didn't allow CSE3063 because student failed prerequisites -> CSE1242 ",
        "",
        "Current Courses: ",
        "CSE3215, IE3081, "
    ],
    "AdvisorName": "RESUL",
    "SemesterNumber": 5,
    "Past Courses": [
        {
            "intGrade": 0,
            "Course": "ATA121",
            "LetterGrade": "FF"
        },
        {
            "intGrade": 72,
            "Course": "MBG1201",
            "LetterGrade": "CC"
        },
        {
            "intGrade": 65,
            "Course": "CSE1200",
            "LetterGrade": "CC"
        },
        {
            "intGrade": 1,
            "Course": "CSE1241",
            "LetterGrade": "FF"
        },
        {
            "intGrade": 88,
            "Course": "MATH1001",
            "LetterGrade": "BA"
        },
        {
            "intGrade": 10,
            "Course": "PHYS1101",
            "LetterGrade": "FF"
        },
        {
            "intGrade": 41,
            "Course": "PHYS1103",
            "LetterGrade": "FF"
        },
        {
            "intGrade": 88,
            "Course": "TRD121",
            "LetterGrade": "BA"
        },
        {
            "intGrade": 71,
            "Course": "ATA122",
            "LetterGrade": "CC"
        },
        {
            "intGrade": 87,
            "Course": "MATH1002",
            "LetterGrade": "BA"
        },
        {
            "intGrade": 51,
            "Course": "MATH2256",
            "LetterGrade": "DD"
        },
        {
            "intGrade": 67,
            "Course": "PHYS1102",
            "LetterGrade": "CC"
        },
        {
            "intGrade": 12,
            "Course": "PHYS1104",
            "LetterGrade": "FF"
        },
        {
            "intGrade": 88,
            "Course": "TRD122",
            "LetterGrade": "BA"
        },
        {
            "intGrade": 49,
            "Course": "CSE2023",
            "LetterGrade": "FD"
        },
        {
            "intGrade": 70,
            "Course": "ECON2004",
            "LetterGrade": "CC"
        },
        {
            "intGrade": 90,
            "Course": "EE2031",
            "LetterGrade": "AA"
        },
        {
            "intGrade": 86,
            "Course": "MATH2055",
            "LetterGrade": "BA"
        },
        {
            "intGrade": 94,
            "Course": "MATH2059",
            "LetterGrade": "AA"
        },
        {
            "intGrade": 93,
            "Course": "CSE2246",
            "LetterGrade": "AA"
        },
        {
            "intGrade": 61,
            "Course": "CSE2138",
            "LetterGrade": "DC"
        },
        {
            "intGrade": 7,
            "Course": "EE2032",
            "LetterGrade": "FF"
        },
        {
            "intGrade": 92,
            "Course": "STAT2253",
            "LetterGrade": "AA"
        },
        {
            "intGrade": 60,
            "Course": "CSE3000",
            "LetterGrade": "DC"
        },
        {
            "intGrade": 89,
            "Course": "YDA2001",
            "LetterGrade": "BA"
        }
    ],
    "StudentName": "OSMAN",
    "StudentSurname": "BULUR",
    "CompletedCredits": 84,
    "StudentId": "150118027",
    "AdvisorSurname": "SARAÇOĞLU ÇEKİÇ"
}