{
    "Current Courses": [
        "CSE1242",
        "EE2032",
        "CSE3038",
        "CSE3048",
        "CSE3264",
        "COM2202"
    ],
    "Execution Trace": [
        "Offered Courses: ",
        "CSE1242, MATH2256, CSE2260, EE2032, CSE3038, CSE3044, CSE3048, CSE3264, IE3235, COM2202, ",
        "(0 NTE), (0 TE), (0 FTE), ",
        "",
        "The system didn't allow MATH2256 because course section is full. (100)",
        "The system didn't allow CSE2260 because student failed prerequisites -> CSE1242 ",
        "The system didn't allow CSE3044 because student failed prerequisites -> CSE3055 ",
        "The system didn't allow IE3235 because student failed prerequisites -> MATH2256 ",
        "",
        "Current Courses: ",
        "CSE1242, EE2032, CSE3038, CSE3048, CSE3264, COM2202, "
    ],
    "AdvisorName": "İLKER BABACAN",
    "SemesterNumber": 6,
    "Past Courses": [
        {
            "intGrade": 93,
            "Course": "ATA121",
            "LetterGrade": "AA"
        },
        {
            "intGrade": 91,
            "Course": "MBG1201",
            "LetterGrade": "AA"
        },
        {
            "intGrade": 95,
            "Course": "CSE1200",
            "LetterGrade": "AA"
        },
        {
            "intGrade": 91,
            "Course": "CSE1241",
            "LetterGrade": "AA"
        },
        {
            "intGrade": 10,
            "Course": "MATH1001",
            "LetterGrade": "FF"
        },
        {
            "intGrade": 63,
            "Course": "PHYS1101",
            "LetterGrade": "DC"
        },
        {
            "intGrade": 86,
            "Course": "PHYS1103",
            "LetterGrade": "BA"
        },
        {
            "intGrade": 21,
            "Course": "TRD121",
            "LetterGrade": "FF"
        },
        {
            "intGrade": 87,
            "Course": "ATA122",
            "LetterGrade": "BA"
        },
        {
            "intGrade": 0,
            "Course": "CSE1242",
            "LetterGrade": "FF"
        },
        {
            "intGrade": 83,
            "Course": "MATH1002",
            "LetterGrade": "BB"
        },
        {
            "intGrade": 17,
            "Course": "MATH2256",
            "LetterGrade": "FF"
        },
        {
            "intGrade": 92,
            "Course": "PHYS1102",
            "LetterGrade": "AA"
        },
        {
            "intGrade": 73,
            "Course": "PHYS1104",
            "LetterGrade": "CC"
        },
        {
            "intGrade": 98,
            "Course": "TRD122",
            "LetterGrade": "AA"
        },
        {
            "intGrade": 71,
            "Course": "CSE2023",
            "LetterGrade": "CC"
        },
        {
            "intGrade": 87,
            "Course": "ECON2004",
            "LetterGrade": "BA"
        },
        {
            "intGrade": 73,
            "Course": "EE2031",
            "LetterGrade": "CC"
        },
        {
            "intGrade": 77,
            "Course": "MATH2055",
            "LetterGrade": "CB"
        },
        {
            "intGrade": 74,
            "Course": "CSE2246",
            "LetterGrade": "CC"
        },
        {
            "intGrade": 85,
            "Course": "CSE2138",
            "LetterGrade": "BA"
        },
        {
            "intGrade": 17,
            "Course": "EE2032",
            "LetterGrade": "FF"
        },
        {
            "intGrade": 63,
            "Course": "STAT2253",
            "LetterGrade": "DC"
        },
        {
            "intGrade": 63,
            "Course": "CSE3000",
            "LetterGrade": "DC"
        },
        {
            "intGrade": 65,
            "Course": "CSE3215",
            "LetterGrade": "CC"
        },
        {
            "intGrade": 59,
            "Course": "IE3081",
            "LetterGrade": "DC"
        },
        {
            "intGrade": 65,
            "Course": "YDIS1002",
            "LetterGrade": "CC"
        }
    ],
    "StudentName": "SEÇİL TÜLÜCE",
    "CompletedCredits": 99,
    "StudentId": "150118046"
}