{
    "Current Courses": [
        "CSE3215",
        "CSE3033",
        "CSE3055",
        "CSE3063",
        "IE3081"
    ],
    "Execution Trace": [
        "Offered Courses: ",
        "ATA121, CSE3215, CSE3033, CSE3055, CSE3063, IE3081, ",
        "(0 NTE), (0 TE), (0 FTE), ",
        "",
        "The system didn't allow ATA121 because course section is full. (100)",
        "",
        "Current Courses: ",
        "CSE3215, CSE3033, CSE3055, CSE3063, IE3081, "
    ],
    "AdvisorName": "TUĞBA",
    "SemesterNumber": 5,
    "Past Courses": [
        {
            "intGrade": 26,
            "Course": "ATA121",
            "LetterGrade": "FF"
        },
        {
            "intGrade": 83,
            "Course": "MBG1201",
            "LetterGrade": "BB"
        },
        {
            "intGrade": 64,
            "Course": "CSE1200",
            "LetterGrade": "DC"
        },
        {
            "intGrade": 58,
            "Course": "CSE1241",
            "LetterGrade": "DC"
        },
        {
            "intGrade": 70,
            "Course": "MATH1001",
            "LetterGrade": "CC"
        },
        {
            "intGrade": 71,
            "Course": "PHYS1101",
            "LetterGrade": "CC"
        },
        {
            "intGrade": 55,
            "Course": "PHYS1103",
            "LetterGrade": "DC"
        },
        {
            "intGrade": 91,
            "Course": "TRD121",
            "LetterGrade": "AA"
        },
        {
            "intGrade": 50,
            "Course": "ATA122",
            "LetterGrade": "DD"
        },
        {
            "intGrade": 81,
            "Course": "CSE1242",
            "LetterGrade": "BB"
        },
        {
            "intGrade": 53,
            "Course": "MATH1002",
            "LetterGrade": "DD"
        },
        {
            "intGrade": 62,
            "Course": "MATH2256",
            "LetterGrade": "DC"
        },
        {
            "intGrade": 81,
            "Course": "PHYS1102",
            "LetterGrade": "BB"
        },
        {
            "intGrade": 72,
            "Course": "PHYS1104",
            "LetterGrade": "CC"
        },
        {
            "intGrade": 62,
            "Course": "TRD122",
            "LetterGrade": "DC"
        },
        {
            "intGrade": 55,
            "Course": "CSE2023",
            "LetterGrade": "DC"
        },
        {
            "intGrade": 55,
            "Course": "CSE2225",
            "LetterGrade": "DC"
        },
        {
            "intGrade": 54,
            "Course": "ECON2004",
            "LetterGrade": "DD"
        },
        {
            "intGrade": 81,
            "Course": "EE2031",
            "LetterGrade": "BB"
        },
        {
            "intGrade": 64,
            "Course": "MATH2055",
            "LetterGrade": "DC"
        },
        {
            "intGrade": 96,
            "Course": "MATH2059",
            "LetterGrade": "AA"
        },
        {
            "intGrade": 95,
            "Course": "CSE2246",
            "LetterGrade": "AA"
        },
        {
            "intGrade": 64,
            "Course": "CSE2138",
            "LetterGrade": "DC"
        },
        {
            "intGrade": 83,
            "Course": "CSE2260",
            "LetterGrade": "BB"
        },
        {
            "intGrade": 36,
            "Course": "EE2032",
            "LetterGrade": "FF"
        },
        {
            "intGrade": 70,
            "Course": "STAT2253",
            "LetterGrade": "CC"
        },
        {
            "intGrade": 82,
            "Course": "CSE3000",
            "LetterGrade": "BB"
        },
        {
            "intGrade": 91,
            "Course": "CAS2005",
            "LetterGrade": "AA"
        }
    ],
    "StudentName": "NEVROZ",
    "StudentSurname": "KAYA",
    "CompletedCredits": 121,
    "StudentId": "150118094",
    "AdvisorSurname": "YENİDOĞAN"
}