{
    "Current Courses": [
        "CSE2246",
        "CSE2138",
        "CSE2260",
        "EE2032",
        "STAT2253"
    ],
    "Execution Trace": [
        "Offered Courses: ",
        "TRD122, CSE2246, CSE2138, CSE2260, EE2032, STAT2253, ",
        "(0 NTE), (0 TE), (0 FTE), ",
        "",
        "The system didn't allow TRD122 because course section is full. (100)",
        "",
        "Current Courses: ",
        "CSE2246, CSE2138, CSE2260, EE2032, STAT2253, "
    ],
    "AdvisorName": "ÜLKÜHAN KÖKSAL",
    "SemesterNumber": 4,
    "Past Courses": [
        {
            "intGrade": 94,
            "Course": "ATA121",
            "LetterGrade": "AA"
        },
        {
            "intGrade": 71,
            "Course": "MBG1201",
            "LetterGrade": "CC"
        },
        {
            "intGrade": 91,
            "Course": "CSE1200",
            "LetterGrade": "AA"
        },
        {
            "intGrade": 76,
            "Course": "CSE1241",
            "LetterGrade": "CB"
        },
        {
            "intGrade": 55,
            "Course": "MATH1001",
            "LetterGrade": "DC"
        },
        {
            "intGrade": 70,
            "Course": "PHYS1101",
            "LetterGrade": "CC"
        },
        {
            "intGrade": 53,
            "Course": "PHYS1103",
            "LetterGrade": "DD"
        },
        {
            "intGrade": 68,
            "Course": "TRD121",
            "LetterGrade": "CC"
        },
        {
            "intGrade": 96,
            "Course": "ATA122",
            "LetterGrade": "AA"
        },
        {
            "intGrade": 79,
            "Course": "CSE1242",
            "LetterGrade": "CB"
        },
        {
            "intGrade": 52,
            "Course": "MATH1002",
            "LetterGrade": "DD"
        },
        {
            "intGrade": 75,
            "Course": "MATH2256",
            "LetterGrade": "CB"
        },
        {
            "intGrade": 55,
            "Course": "PHYS1102",
            "LetterGrade": "DC"
        },
        {
            "intGrade": 77,
            "Course": "PHYS1104",
            "LetterGrade": "CB"
        },
        {
            "intGrade": 27,
            "Course": "TRD122",
            "LetterGrade": "FF"
        },
        {
            "intGrade": 81,
            "Course": "CSE2023",
            "LetterGrade": "BB"
        },
        {
            "intGrade": 91,
            "Course": "CSE2225",
            "LetterGrade": "AA"
        },
        {
            "intGrade": 71,
            "Course": "ECON2004",
            "LetterGrade": "CC"
        },
        {
            "intGrade": 58,
            "Course": "EE2031",
            "LetterGrade": "DC"
        },
        {
            "intGrade": 85,
            "Course": "MATH2055",
            "LetterGrade": "BA"
        },
        {
            "intGrade": 70,
            "Course": "MATH2059",
            "LetterGrade": "CC"
        },
        {
            "intGrade": 90,
            "Course": "CAS1001",
            "LetterGrade": "AA"
        }
    ],
    "StudentName": "ÇAVLAN YUMURTAŞ",
    "CompletedCredits": 89,
    "StudentId": "150119083"
}